{
  "AltLookAngle": {
    "x": 0,
    "y": 0,
    "z": 0
  },
  "Autoraise": true,
  "ColorDiffuse": {
    "b": 1,
    "g": 1,
    "r": 1
  },
  "CustomPDF": {
    "PDFPage": 0,
    "PDFPageOffset": 0,
    "PDFPassword": "",
    "PDFUrl": "http://cloud-3.steamusercontent.com/ugc/2051989444907893379/EC7182ED36C275141B43C291AE03A583EBD3D66D/"
  },
  "Description": "",
  "DragSelectable": true,
  "GMNotes": "",
  "GUID": "ee98ef",
  "Grid": true,
  "GridProjection": false,
  "Hands": false,
  "HideWhenFaceDown": false,
  "IgnoreFoW": false,
  "LayoutGroupSortIndex": 0,
  "Locked": false,
  "LuaScript": "",
  "LuaScriptState": "",
  "MeasureMovement": false,
  "Name": "Custom_PDF",
  "Nickname": "",
  "Snap": true,
  "Sticky": true,
  "Tooltip": true,
  "Transform": {
    "posX": -29.34,
    "posY": 3.637,
    "posZ": -86.002,
    "rotX": 0,
    "rotY": 270,
    "rotZ": 0,
    "scaleX": 5.46,
    "scaleY": 1,
    "scaleZ": 5.46
  },
  "Value": 0,
  "XmlUI": ""
}
