{
  "AltLookAngle": {
    "x": 0,
    "y": 0,
    "z": 0
  },
  "Autoraise": true,
  "ColorDiffuse": {
    "b": 1,
    "g": 1,
    "r": 1
  },
  "CustomMesh": {
    "CastShadows": true,
    "ColliderURL": "http://cloud-3.steamusercontent.com/ugc/943949966265929204/A38BB5D72419E6298385556D931877C0A1A55C17/",
    "Convex": true,
    "CustomShader": {
      "FresnelStrength": 0,
      "SpecularColor": {
        "b": 0.339915335,
        "g": 0.507659256,
        "r": 0.7222887
      },
      "SpecularIntensity": 0.4,
      "SpecularSharpness": 7
    },
    "DiffuseURL": "http://cloud-3.steamusercontent.com/ugc/254843371583187306/6844B833AD55B9A34095067B201B311E1348325F/",
    "MaterialIndex": 2,
    "MeshURL": "http://cloud-3.steamusercontent.com/ugc/943949966265929204/A38BB5D72419E6298385556D931877C0A1A55C17/",
    "NormalURL": "",
    "TypeIndex": 0
  },
  "Description": "Include this in custom content for clue spawning!",
  "DragSelectable": true,
  "GMNotes": "",
  "GUID": "c5afbe",
  "Grid": true,
  "GridProjection": false,
  "Hands": false,
  "HideWhenFaceDown": false,
  "IgnoreFoW": false,
  "LayoutGroupSortIndex": 0,
  "Locked": false,
  "LuaScript": "-- set true to enable debug logging\r\nDEBUG = false\r\n\r\nfunction log(message)\r\n  if DEBUG then\r\n    print(message)\r\n  end\r\nend\r\n\r\n--[[\r\nKnown locations and clues. We check this to determine if we should\r\natttempt to spawn clues, first we look for \u003cLOCATION_NAME\u003e_\u003cGUID\u003e and if\r\nwe find nothing we look for \u003cLOCATION_NAME\u003e\r\nformat is [location_guid -\u003e clueCount]\r\n]]\r\nLOCATIONS_DATA_JSON = [[\r\n{\r\n  \"San Francisco\": {\"type\": \"fixed\", \"value\": 1, \"clueSide\": \"back\"},\r\n  \"\tArkham\": {\"type\": \"perPlayer\", \"value\": 1, \"clueSide\": \"back\"},\r\n  \"Buenos Aires\": {\"type\": \"fixed\", \"value\": 2, \"clueSide\": \"back\"},\r\n  \"\tLondon\": {\"type\": \"perPlayer\", \"value\": 2, \"clueSide\": \"front\"},\r\n  \"Rome\": {\"type\": \"perPlayer\", \"value\": 3, \"clueSide\": \"front\"},\r\n  \"Istanbul\": {\"type\": \"perPlayer\", \"value\": 4, \"clueSide\": \"front\"},\r\n  \"Tokyo_123abc\": {\"type\": \"perPlayer\", \"value\": 0, \"clueSide\": \"back\"},\r\n  \"Tokyo_456efg\": {\"type\": \"perPlayer\", \"value\": 4, \"clueSide\": \"back\"},\r\n  \"Tokyo\": {\"type\": \"fixed\", \"value\": 2, \"clueSide\": \"back\"},\r\n  \"Shanghai_123\": {\"type\": \"fixed\", \"value\": 12, \"clueSide\": \"front\"},\r\n  \"Sydney\": {\"type\": \"fixed\", \"value\": 0, \"clueSide\": \"front\"},\r\n  \"Side Yard\": {\"type\": \"perPlayer\", \"value\": 1, \"clueSide\": \"front\"},\r\n  \"Backyard\": {\"type\": \"perPlayer\", \"value\": 2, \"clueSide\": \"front\"},\r\n  \"Entry Hall\": {\"type\": \"perPlayer\", \"value\": 2, \"clueSide\": \"front\"},\r\n  \"Living Room\": {\"type\": \"perPlayer\", \"value\": 1, \"clueSide\": \"front\"},\r\n  \"Dining Room\": {\"type\": \"perPlayer\", \"value\": 2, \"clueSide\": \"front\"},\r\n  \"Kitchen\": {\"type\": \"perPlayer\", \"value\": 2, \"clueSide\": \"front\"},\r\n  \"Bathroom\": {\"type\": \"perPlayer\", \"value\": 1, \"clueSide\": \"front\"},\r\n  \"Study\": {\"type\": \"perPlayer\", \"value\": 3, \"clueSide\": \"front\"},\r\n  \"Whittle Residence\": {\"type\": \"perPlayer\", \"value\": 1, \"clueSide\": \"front\"},\r\n  \"Smitty's Diner\": {\"type\": \"perPlayer\", \"value\": 2, \"clueSide\": \"front\"},\r\n  \"Whittle Residence\": {\"type\": \"perPlayer\", \"value\": 1, \"clueSide\": \"front\"},\r\n  \"Brantford Police Station\": {\"type\": \"perPlayer\", \"value\": 1, \"clueSide\": \"front\"},\r\n  \"Brantford City Hall\": {\"type\": \"perPlayer\", \"value\": 1, \"clueSide\": \"front\"},\r\n  \"Telephone Dispatch Office\": {\"type\": \"perPlayer\", \"value\": 2, \"clueSide\": \"front\"},\r\n  \"Municipal Hospital\": {\"type\": \"perPlayer\", \"value\": 2, \"clueSide\": \"front\"},\r\n  \"Chronicle Archives\": {\"type\": \"perPlayer\", \"value\": 3, \"clueSide\": \"front\"},\r\n  \"St. Simon's Church\": {\"type\": \"perPlayer\", \"value\": 1, \"clueSide\": \"front\"},\r\n  \"Municipal Mental Ward\": {\"type\": \"perPlayer\", \"value\": 2, \"clueSide\": \"front\"},\r\n  \"Boorstein Clinic\": {\"type\": \"perPlayer\", \"value\": 2, \"clueSide\": \"front\"},\r\n  \"Howell Asylum\": {\"type\": \"perPlayer\", \"value\": 2, \"clueSide\": \"front\"},\r\n  \"Parlor\": {\"type\": \"perPlayer\", \"value\": 1, \"clueSide\": \"front\"},\r\n  \"Foyer\": {\"type\": \"perPlayer\", \"value\": 1, \"clueSide\": \"front\"},\r\n  \"Veranda\": {\"type\": \"perPlayer\", \"value\": 1, \"clueSide\": \"front\"},\r\n  \"Reception Room\": {\"type\": \"perPlayer\", \"value\": 2, \"clueSide\": \"front\"},\r\n  \"Spiral Staircase\": {\"type\": \"perPlayer\", \"value\": 1, \"clueSide\": \"front\"},\r\n  \"Master Bedroom\": {\"type\": \"perPlayer\", \"value\": 2, \"clueSide\": \"front\"},\r\n  \"Abandoned Room\": {\"type\": \"perPlayer\", \"value\": 1, \"clueSide\": \"front\"},\r\n  \"Attic\": {\"type\": \"perPlayer\", \"value\": 3, \"clueSide\": \"front\"},\r\n  \"Rampant Jungle\": {\"type\": \"perPlayer\", \"value\": 1, \"clueSide\": \"front\"},\r\n  \"Overgrown Streets\": {\"type\": \"perPlayer\", \"value\": 2, \"clueSide\": \"front\"},\r\n  \"Tangled Neighborhood\": {\"type\": \"perPlayer\", \"value\": 2, \"clueSide\": \"front\"},\r\n  \"Shrouded Clearing\": {\"type\": \"perPlayer\", \"value\": 1, \"clueSide\": \"front\"},\r\n  \"Dense Thicket\": {\"type\": \"perPlayer\", \"value\": 1, \"clueSide\": \"front\"}\r\n}\r\n]]\r\n\r\n\r\nPLAYER_CARD_DATA_JSON = [[\r\n{\r\n  \"Tool Belt (0)\": {\r\n    \"tokenType\": \"resource\",\r\n    \"tokenCount\": 2\r\n  },\r\n  \"Tool Belt (3)\": {\r\n    \"tokenType\": \"resource\",\r\n    \"tokenCount\": 4\r\n  },\r\n  \"Yithian Rifle\": {\r\n    \"tokenType\": \"resource\",\r\n    \"tokenCount\": 3\r\n  },\r\n  \"xxx\": {\r\n    \"tokenType\": \"resource\",\r\n    \"tokenCount\": 3\r\n  }\r\n}\r\n]]\r\n\r\nHIDDEN_CARD_DATA = {\r\n  \"Unpleasant Card (Doom)\",\r\n  \"Unpleasant Card (Gloom)\",\r\n  \"The Case of the Scarlet DOOOOOM!\"\r\n}\r\n\r\nLOCATIONS_DATA = JSON.decode(LOCATIONS_DATA_JSON)\r\nPLAYER_CARD_DATA = JSON.decode(PLAYER_CARD_DATA_JSON)\r\n\r\nfunction onload(save_state)\r\n  local playArea = getObjectFromGUID('721ba2')\r\n  playArea.call(\"updateLocations\", {self.getGUID()})\r\n  local playerMatWhite = getObjectFromGUID('8b081b')\r\n  playerMatWhite.call(\"updatePlayerCards\", {self.getGUID()})\r\n  local playerMatOrange = getObjectFromGUID('bd0ff4')\r\n  playerMatOrange.call(\"updatePlayerCards\", {self.getGUID()})\r\n  local playerMatGreen = getObjectFromGUID('383d8b')\r\n  playerMatGreen.call(\"updatePlayerCards\", {self.getGUID()})\r\n  local playerMatRed = getObjectFromGUID('0840d5')\r\n  playerMatRed.call(\"updatePlayerCards\", {self.getGUID()})\r\n  local dataHelper = getObjectFromGUID('708279')\r\n  dataHelper.call(\"updateHiddenCards\", {self.getGUID()})\r\nend",
  "LuaScriptState": "",
  "LuaScript_path": "JumanjiCustomDataHelper.c5afbe.ttslua",
  "MeasureMovement": false,
  "Name": "Custom_Model",
  "Nickname": "Jumanji Custom Data Helper",
  "Snap": true,
  "Sticky": true,
  "Tooltip": true,
  "Transform": {
    "posX": -0.260230362,
    "posY": 1.62692189,
    "posZ": -16.4254951,
    "rotX": 359.919739,
    "rotY": 269.9958,
    "rotZ": 0.0168303363,
    "scaleX": 0.5000004,
    "scaleY": 0.5000004,
    "scaleZ": 0.5000004
  },
  "Value": 0,
  "XmlUI": ""
}