{
  "AltLookAngle": {
    "x": 0,
    "y": 0,
    "z": 0
  },
  "Autoraise": true,
  "CardID": 320300,
  "ColorDiffuse": {
    "b": 0.71324,
    "g": 0.71324,
    "r": 0.71324
  },
  "CustomDeck": {
    "3203": {
      "BackIsHidden": true,
      "BackURL": "https://i.imgur.com/sRsWiSG.jpg/",
      "FaceURL": "https://i.imgur.com/WKbgizX.jpg",
      "NumHeight": 1,
      "NumWidth": 1,
      "Type": 0,
      "UniqueBack": false
    }
  },
  "Description": "",
  "DragSelectable": true,
  "GMNotes_path": "Bloodborne-CityoftheUnseen0175.81651b/5TheAltarofDespair.9b4b47/EncounterDeckSetup.fa41bc/Act2Additions-9orMoreRecognition.4510fb/Act2Additions.58cfa8/HypogeanSnatcher.e00002.gmnotes",
  "GUID": "e00002",
  "Grid": true,
  "GridProjection": false,
  "Hands": true,
  "HideWhenFaceDown": true,
  "IgnoreFoW": false,
  "LayoutGroupSortIndex": 0,
  "Locked": false,
  "LuaScript": "",
  "LuaScriptState": "",
  "MeasureMovement": false,
  "Name": "Card",
  "Nickname": "Hypogean Snatcher",
  "SidewaysCard": false,
  "Snap": true,
  "Sticky": true,
  "Tags": [
    "ScenarioCard"
  ],
  "Tooltip": true,
  "Transform": {
    "posX": -30.479,
    "posY": 2.524,
    "posZ": -43.768,
    "rotX": 0,
    "rotY": 179,
    "rotZ": 0,
    "scaleX": 1,
    "scaleY": 1,
    "scaleZ": 1
  },
  "Value": 0,
  "XmlUI": ""
}
