{
  "AltLookAngle": {
    "x": 0,
    "y": 0,
    "z": 0
  },
  "AttachedSnapPoints": [
    {
      "Position": {
        "x": 0,
        "y": 0.1,
        "z": 0.05
      }
    }
  ],
  "Autoraise": true,
  "ColorDiffuse": {
    "b": 0,
    "g": 0,
    "r": 0
  },
  "CustomImage": {
    "CustomTile": {
      "Stackable": false,
      "Stretch": true,
      "Thickness": 0.1,
      "Type": 3
    },
    "ImageScalar": 1,
    "ImageSecondaryURL": "",
    "ImageURL": "https://steamusercontent-a.akamaihd.net/ugc/2466368617700119071/AB8294EEBA3A219CDCE287323B764D13E2A43822/",
    "WidthScale": 0
  },
  "Description": "This tool can generate a description for your deck on ArkhamDB that will instruct the Deck Importer to add the specified cards.\nThe cards need to be available (either from the AllCardsBag or the 'Additional Playercards Bag'.",
  "DragSelectable": true,
  "GMNotes": "",
  "GUID": "240522",
  "Grid": true,
  "GridProjection": false,
  "Hands": false,
  "HideWhenFaceDown": false,
  "IgnoreFoW": false,
  "LayoutGroupSortIndex": 0,
  "Locked": true,
  "LuaScript": "require(\"arkhamdb/DeckInstructionGenerator\")",
  "LuaScriptState": "",
  "MeasureMovement": false,
  "Name": "Custom_Tile",
  "Nickname": "Deck Instruction Generator",
  "Snap": true,
  "Sticky": true,
  "Tooltip": true,
  "Transform": {
    "posX": -17.5,
    "posY": 1.481,
    "posZ": 83,
    "rotX": 0,
    "rotY": 270,
    "rotZ": 0,
    "scaleX": 3,
    "scaleY": 1,
    "scaleZ": 3
  },
  "Value": 0,
  "XmlUI": ""
}