{
  "AltLookAngle": {
    "x": 0,
    "y": 0,
    "z": 0
  },
  "Autoraise": true,
  "ColorDiffuse": {
    "b": 0,
    "g": 0,
    "r": 0
  },
  "CustomImage": {
    "CustomTile": {
      "Stackable": false,
      "Stretch": true,
      "Thickness": 0.495000154,
      "Type": 0
    },
    "ImageScalar": 1,
    "ImageSecondaryURL": "",
    "ImageURL": "https://steamusercontent-a.akamaihd.net/ugc/273974515701259432/A09A20BE6300EAB285858E76A03BD781EE3845B5/",
    "WidthScale": 0
  },
  "Description": "",
  "DragSelectable": true,
  "GMNotes": "",
  "GUID": "463022",
  "Grid": true,
  "GridProjection": false,
  "Hands": false,
  "HideWhenFaceDown": false,
  "IgnoreFoW": false,
  "LayoutGroupSortIndex": 0,
  "Locked": true,
  "LuaScript": "",
  "LuaScriptState": "",
  "MeasureMovement": false,
  "Name": "Custom_Tile",
  "Nickname": "Panel",
  "Snap": true,
  "Sticky": true,
  "Tags": [
    "NotInteractable"
  ],
  "Tooltip": false,
  "Transform": {
    "posX": 77.99,
    "posY": 0.65,
    "posZ": 0,
    "rotX": 0,
    "rotY": 270,
    "rotZ": 0,
    "scaleX": 25,
    "scaleY": 1,
    "scaleZ": 2.26
  },
  "Value": 0,
  "XmlUI": ""
}
