{
  "AltLookAngle": {
    "x": 0,
    "y": 0,
    "z": 0
  },
  "Autoraise": true,
  "CardID": 266103,
  "ColorDiffuse": {
    "b": 0.71324,
    "g": 0.71324,
    "r": 0.71324
  },
  "CustomDeck": {
    "2661": {
      "BackIsHidden": false,
      "BackURL": "http://cloud-3.steamusercontent.com/ugc/778493732358554721/C95D5B3564369BBC90833CA16DFC670FEFB80205/",
      "FaceURL": "http://cloud-3.steamusercontent.com/ugc/778493732358554721/C95D5B3564369BBC90833CA16DFC670FEFB80205/",
      "NumHeight": 2,
      "NumWidth": 2,
      "Type": 0,
      "UniqueBack": true
    }
  },
  "Description": "",
  "DragSelectable": true,
  "GMNotes": "",
  "GUID": "91c83e",
  "Grid": true,
  "GridProjection": false,
  "Hands": true,
  "HideWhenFaceDown": false,
  "IgnoreFoW": false,
  "LayoutGroupSortIndex": 0,
  "Locked": true,
  "LuaScript": "",
  "LuaScriptState": "",
  "MeasureMovement": false,
  "Name": "Card",
  "Nickname": "Rules Index",
  "SidewaysCard": false,
  "Snap": true,
  "Sticky": true,
  "Tooltip": true,
  "Transform": {
    "posX": -61,
    "posY": 1.27,
    "posZ": 59,
    "rotX": 0,
    "rotY": 270,
    "rotZ": 0,
    "scaleX": 5.88,
    "scaleY": 1,
    "scaleZ": 5.88
  },
  "Value": 0,
  "XmlUI": ""
}
