{
  "AltLookAngle": {
    "x": 0,
    "y": 0,
    "z": 0
  },
  "Autoraise": true,
  "ColorDiffuse": {
    "b": 0.713235259,
    "g": 0.713235259,
    "r": 0.713235259
  },
  "ContainedObjects_order": [
    "FinePrint.39452d",
    "SellYourSoul.180b5b",
    "ThePriceofFailure.dc5b38",
    "AccursedFate.85e7d9",
    "TheBellTolls.6cbc01"
  ],
  "ContainedObjects_path": "Advanced.15e75e",
  "CustomDeck": {
    "5376": {
      "BackIsHidden": true,
      "BackURL": "https://i.imgur.com/EcbhVuh.jpg/",
      "FaceURL": "http://cloud-3.steamusercontent.com/ugc/775107869048626382/DA1F5817A4067A74D883201F1AFAC096646A455B/",
      "NumHeight": 7,
      "NumWidth": 10,
      "Type": 0,
      "UniqueBack": false
    },
    "5452": {
      "BackIsHidden": true,
      "BackURL": "https://i.imgur.com/EcbhVuh.jpg/",
      "FaceURL": "http://cloud-3.steamusercontent.com/ugc/1487830656537158415/2EBB208AA994ED70FD0FEB02D4E4FE78FE43EE02/",
      "NumHeight": 7,
      "NumWidth": 10,
      "Type": 0,
      "UniqueBack": false
    }
  },
  "DeckIDs": [
    545213,
    545214,
    537612,
    537608,
    537609
  ],
  "Description": "",
  "DragSelectable": true,
  "GMNotes": "",
  "GUID": "15e75e",
  "Grid": true,
  "GridProjection": false,
  "Hands": false,
  "HideWhenFaceDown": true,
  "IgnoreFoW": false,
  "LayoutGroupSortIndex": 0,
  "Locked": false,
  "LuaScript": "",
  "LuaScriptState": "",
  "MeasureMovement": false,
  "Name": "Deck",
  "Nickname": "Advanced",
  "SidewaysCard": false,
  "Snap": true,
  "Sticky": true,
  "Tooltip": true,
  "Transform": {
    "posX": -24.4534,
    "posY": 1.3055,
    "posZ": 83.2946,
    "rotX": 0,
    "rotY": 270,
    "rotZ": 180,
    "scaleX": 1,
    "scaleY": 1,
    "scaleZ": 1
  },
  "Value": 0,
  "XmlUI": ""
}