{
  "labels": [
    {
      "displayed": "import_configuration_provider",
      "normalized": "import_configuration_provider"
    },
    {
      "displayed": "AllCardsHotfix",
      "normalized": "allcardshotfix"
    },
    {
      "displayed": "LinkedPhaseTracker",
      "normalized": "linkedphasetracker"
    },
    {
      "displayed": "DoNotReady",
      "normalized": "donotready"
    },
    {
      "displayed": "displacement_excluded",
      "normalized": "displacement_excluded"
    },
    {
      "displayed": "PlayerCard",
      "normalized": "playercard"
    },
    {
      "displayed": "CleanUpHelper_ignore",
      "normalized": "cleanuphelper_ignore"
    },
    {
      "displayed": "Asset",
      "normalized": "asset"
    },
    {
      "displayed": "ScenarioCard",
      "normalized": "scenariocard"
    },
    {
      "displayed": "Location",
      "normalized": "location"
    },
    {
      "displayed": "tempToken",
      "normalized": "temptoken"
    },
    {
      "displayed": "Minicard",
      "normalized": "minicard"
    },
    {
      "displayed": "DoomCounter_ignore",
      "normalized": "doomcounter_ignore"
    },
    {
      "displayed": "Investigator",
      "normalized": "investigator"
    },
    {
      "displayed": "chaosBag",
      "normalized": "chaosbag"
    },
    {
      "displayed": "LargeBox",
      "normalized": "largebox"
    },
    {
      "displayed": "CampaignBox",
      "normalized": "campaignbox"
    },
    {
      "displayed": "CameraZoom_ignore",
      "normalized": "camerazoom_ignore"
    },
    {
      "displayed": "UniversalToken",
      "normalized": "universaltoken"
    },
    {
      "displayed": "CampaignLog",
      "normalized": "campaignlog"
    },
    {
      "displayed": "CampaignGuide",
      "normalized": "campaignguide"
    }
  ]
}
