{
  "AltLookAngle": {
    "x": 0,
    "y": 0,
    "z": 0
  },
  "Autoraise": true,
  "CardID": 530000,
  "ColorDiffuse": {
    "b": 0.71324,
    "g": 0.71324,
    "r": 0.71324
  },
  "CustomDeck": {
    "5300": {
      "BackIsHidden": true,
      "BackURL": "http://cloud-3.steamusercontent.com/ugc/1461933574036605747/66F5F6903F78214DDB7420F5022C9CDEC4D85464/",
      "FaceURL": "http://cloud-3.steamusercontent.com/ugc/1997946062963946573/46744C9B26EF5795EF3B93F694F7FED490B188C1/",
      "NumHeight": 1,
      "NumWidth": 1,
      "Type": 0,
      "UniqueBack": false
    }
  },
  "Description": "",
  "DragSelectable": true,
  "GMNotes_path": "TheColourOutofOz.be7d21/GillikinCountry.ed243f/ReeratheRed.59095c.gmnotes",
  "GUID": "59095c",
  "Grid": true,
  "GridProjection": false,
  "Hands": true,
  "HideWhenFaceDown": true,
  "IgnoreFoW": false,
  "LayoutGroupSortIndex": 0,
  "Locked": false,
  "LuaScript": "",
  "LuaScriptState": "",
  "MeasureMovement": false,
  "Name": "CardCustom",
  "Nickname": "Reera the Red",
  "SidewaysCard": false,
  "Snap": true,
  "Sticky": true,
  "Tags": [
    "PlayerCard",
    "Asset"
  ],
  "Tooltip": true,
  "Transform": {
    "posX": -5.356,
    "posY": 1.597,
    "posZ": 13.786,
    "rotX": 0,
    "rotY": 270,
    "rotZ": 0,
    "scaleX": 1,
    "scaleY": 1,
    "scaleZ": 1
  },
  "Value": 0,
  "XmlUI": ""
}
