{
  "AltLookAngle": {
    "x": 0,
    "y": 0,
    "z": 0
  },
  "Autoraise": true,
  "ColorDiffuse": {
    "b": 1,
    "g": 1,
    "r": 1
  },
  "CustomImage": {
    "CustomToken": {
      "MergeDistancePixels": 5,
      "Stackable": true,
      "StandUp": false,
      "Thickness": 0.3
    },
    "ImageScalar": 1,
    "ImageSecondaryURL": "",
    "ImageURL": "http://cloud-3.steamusercontent.com/ugc/1758068501357192910/11DDDC7EF621320962FDCF3AE3211D5EDC3D1573/",
    "WidthScale": 0
  },
  "Description": "",
  "DragSelectable": true,
  "GMNotes": "",
  "GUID": "edc175",
  "Grid": true,
  "GridProjection": false,
  "Hands": false,
  "HideWhenFaceDown": false,
  "IgnoreFoW": false,
  "LayoutGroupSortIndex": 0,
  "Locked": false,
  "LuaScript": "",
  "LuaScriptState": "",
  "MeasureMovement": false,
  "Name": "Custom_Token",
  "Nickname": "",
  "Snap": false,
  "Sticky": true,
  "Tooltip": true,
  "Transform": {
    "posX": -22.664,
    "posY": 1.67,
    "posZ": -3.481,
    "rotX": 0,
    "rotY": 265,
    "rotZ": 0,
    "scaleX": 0.33,
    "scaleY": 1,
    "scaleZ": 0.33
  },
  "Value": 0,
  "XmlUI": ""
}
