{
  "AltLookAngle": {
    "x": 0,
    "y": 0,
    "z": 0
  },
  "Autoraise": true,
  "ColorDiffuse": {
    "b": 1,
    "g": 1,
    "r": 1
  },
  "CustomImage": {
    "CustomTile": {
      "Stackable": true,
      "Stretch": true,
      "Thickness": 0.1,
      "Type": 3
    },
    "ImageScalar": 1,
    "ImageSecondaryURL": "http://cloud-3.steamusercontent.com/ugc/1763698230708354798/23612793AE012CDFD906D19FAC167E81F3ED78F7/",
    "ImageURL": "http://cloud-3.steamusercontent.com/ugc/1763698230708340666/402C6AA9EACD3D74A286A7BB3F59FADFED47D95E/",
    "WidthScale": 0
  },
  "Description": "",
  "DragSelectable": true,
  "GMNotes": "",
  "GUID": "8007d3",
  "Grid": false,
  "GridProjection": false,
  "Hands": false,
  "HideWhenFaceDown": false,
  "IgnoreFoW": false,
  "LayoutGroupSortIndex": 0,
  "Locked": false,
  "LuaScript": "",
  "LuaScriptState": "",
  "MeasureMovement": false,
  "Name": "Custom_Tile",
  "Nickname": "Jacqueline Fine",
  "Snap": false,
  "States": {
    "2": {
      "AltLookAngle": {
        "x": 0,
        "y": 0,
        "z": 0
      },
      "Autoraise": true,
      "ColorDiffuse": {
        "b": 1,
        "g": 1,
        "r": 1
      },
      "CustomImage": {
        "CustomTile": {
          "Stackable": true,
          "Stretch": true,
          "Thickness": 0.1,
          "Type": 3
        },
        "ImageScalar": 1,
        "ImageSecondaryURL": "http://cloud-3.steamusercontent.com/ugc/1763698230708354840/A8B4F12E6DD0A1BC641627FD3170671F34551F10/",
        "ImageURL": "http://cloud-3.steamusercontent.com/ugc/1763698230708340716/31853BB4E6FB5C7C6EB93B48698DEB3DB9198DFD/",
        "WidthScale": 0
      },
      "Description": "",
      "DragSelectable": true,
      "GMNotes": "",
      "GUID": "0896ca",
      "Grid": false,
      "GridProjection": false,
      "Hands": false,
      "HideWhenFaceDown": false,
      "IgnoreFoW": false,
      "LayoutGroupSortIndex": 0,
      "Locked": false,
      "LuaScript": "",
      "LuaScriptState": "",
      "MeasureMovement": false,
      "Name": "Custom_Tile",
      "Nickname": "Jacqueline Fine",
      "Snap": false,
      "Sticky": true,
      "Tooltip": true,
      "Transform": {
        "posX": -0.402367145,
        "posY": 0.9600022,
        "posZ": -2.61121845,
        "rotX": -0.00001754304,
        "rotY": 180,
        "rotZ": -0.00000187718229,
        "scaleX": 0.5657107,
        "scaleY": 1,
        "scaleZ": 0.5657107
      },
      "Value": 0,
      "XmlUI": ""
    }
  },
  "Sticky": true,
  "Tooltip": true,
  "Transform": {
    "posX": -3.893,
    "posY": 3.026,
    "posZ": -3.189,
    "rotX": 0,
    "rotY": 180,
    "rotZ": 0,
    "scaleX": 0.57,
    "scaleY": 1,
    "scaleZ": 0.57
  },
  "Value": 0,
  "XmlUI": ""
}
