{
  "AltLookAngle": {
    "x": 0,
    "y": 0,
    "z": 0
  },
  "Autoraise": true,
  "CardID": 267902,
  "ColorDiffuse": {
    "b": 0.713235259,
    "g": 0.713235259,
    "r": 0.713235259
  },
  "CustomDeck": {
    "2679": {
      "BackIsHidden": true,
      "BackURL": "http://cloud-3.steamusercontent.com/ugc/1461933361191993988/FE126C3E21593398897E3C691A0AEA8D9B73A614/",
      "FaceURL": "http://cloud-3.steamusercontent.com/ugc/1847049778276368674/4B6C8D8422818E8E05176CF59136D59CF433FA7B/",
      "NumHeight": 2,
      "NumWidth": 2,
      "Type": 0,
      "UniqueBack": false
    }
  },
  "Description": "",
  "DragSelectable": true,
  "GMNotes": "",
  "GUID": "6c30e3",
  "Grid": true,
  "GridProjection": false,
  "Hands": true,
  "HideWhenFaceDown": true,
  "IgnoreFoW": false,
  "LayoutGroupSortIndex": 0,
  "Locked": false,
  "LuaScript": "",
  "LuaScriptState": "",
  "MeasureMovement": false,
  "Name": "Card",
  "Nickname": "Overheated",
  "SidewaysCard": false,
  "Snap": true,
  "Sticky": true,
  "Tooltip": true,
  "Transform": {
    "posX": 24.5949345,
    "posY": 1.37379181,
    "posZ": -47.6089973,
    "rotX": 0.0208919179,
    "rotY": 270.0027,
    "rotZ": 0.016305685,
    "scaleX": 1,
    "scaleY": 1,
    "scaleZ": 1
  },
  "Value": 0,
  "XmlUI": ""
}