{
  "AltLookAngle": {
    "x": 0,
    "y": 0,
    "z": 0
  },
  "Autoraise": true,
  "ColorDiffuse": {
    "b": 1,
    "g": 1,
    "r": 1
  },
  "CustomImage": {
    "CustomToken": {
      "MergeDistancePixels": 15,
      "Stackable": false,
      "StandUp": false,
      "Thickness": 0.1
    },
    "ImageScalar": 1,
    "ImageSecondaryURL": "",
    "ImageURL": "https://i.ibb.co/9qK9Fzd/Cyclopean-3-Private-Lives-Christian-Bravery.png",
    "WidthScale": 0
  },
  "Description": "",
  "DragSelectable": true,
  "GMNotes": "",
  "GUID": "940388",
  "Grid": true,
  "GridProjection": false,
  "Hands": false,
  "HideWhenFaceDown": false,
  "IgnoreFoW": false,
  "LayoutGroupSortIndex": 0,
  "Locked": false,
  "LuaScriptState": "",
  "LuaScript_path": "Fan-MadeAccessories.aa8b38/PlaymatCustomsByBLMintTeaFan.67d8c7/CyclopeanFoundations.c87ef3/CF-3.940388.ttslua",
  "MeasureMovement": false,
  "Name": "Custom_Token",
  "Nickname": "CF - 3",
  "Snap": true,
  "Sticky": true,
  "Tags": [
    "cfmat_memory_object"
  ],
  "Tooltip": true,
  "Transform": {
    "posX": 40.3041,
    "posY": 1.3374,
    "posZ": -56.6115,
    "rotX": 0,
    "rotY": 270,
    "rotZ": 0,
    "scaleX": 1,
    "scaleY": 1,
    "scaleZ": 1
  },
  "Value": 0,
  "XmlUI": ""
}