{
  "AltLookAngle": {
    "x": 0,
    "y": 0,
    "z": 0
  },
  "Autoraise": true,
  "CardID": 234901,
  "ColorDiffuse": {
    "b": 0.713235259,
    "g": 0.713235259,
    "r": 0.713235259
  },
  "CustomDeck": {
    "2349": {
      "BackIsHidden": true,
      "BackURL": "http://cloud-3.steamusercontent.com/ugc/1016065907887642390/2CC878F26205C80F4B8D69DE3A4433804A31AABF/",
      "FaceURL": "http://cloud-3.steamusercontent.com/ugc/1016065907887640918/BF3A963B745EF2047ABDFC524AEE4EA0145A04F4/",
      "NumHeight": 7,
      "NumWidth": 10,
      "Type": 0,
      "UniqueBack": true
    }
  },
  "Description": "The Professor",
  "DragSelectable": true,
  "GMNotes": "{\n  \"id\": \"60201\",\n  \"type\": \"Investigator\",\n  \"class\": \"Seeker\",\n  \"traits\": \"Miskatonic.\",\n  \"willpowerIcons\": 4,\n  \"intellectIcons\": 5,\n  \"combatIcons\": 1,\n  \"agilityIcons\": 2,\n  \"cycle\": \"Investigator Packs\"\n}",
  "GUID": "1fa944",
  "Grid": true,
  "GridProjection": false,
  "Hands": true,
  "HideWhenFaceDown": false,
  "IgnoreFoW": false,
  "LayoutGroupSortIndex": 0,
  "Locked": false,
  "LuaScript": "",
  "LuaScriptState": "",
  "MeasureMovement": false,
  "Name": "Card",
  "Nickname": "Harvey Walters",
  "SidewaysCard": true,
  "Snap": true,
  "Sticky": true,
  "Tags": [
    "PlayerCard"
  ],
  "Tooltip": true,
  "Transform": {
    "posX": 18.4484577,
    "posY": 1.60544109,
    "posZ": -73.08731,
    "rotX": 0.02826287,
    "rotY": 179.9997,
    "rotZ": 359.976379,
    "scaleX": 1.1,
    "scaleY": 1,
    "scaleZ": 1.1
  },
  "Value": 0,
  "XmlUI": ""
}