{
  "AltLookAngle": {
    "x": 0,
    "y": 0,
    "z": 0
  },
  "Autoraise": true,
  "CardID": 450104,
  "ColorDiffuse": {
    "b": 0.71324,
    "g": 0.71324,
    "r": 0.71324
  },
  "CustomDeck": {
    "4501": {
      "BackIsHidden": true,
      "BackURL": "http://cloud-3.steamusercontent.com/ugc/1656727981627737648/F371339538812F68E38AAC0D520C525250DAC5C0/",
      "FaceURL": "http://cloud-3.steamusercontent.com/ugc/1656727981627737050/3CFF9E3825033909543AD1CF843361D9243538EE/",
      "NumHeight": 2,
      "NumWidth": 4,
      "Type": 0,
      "UniqueBack": true
    }
  },
  "Description": "The Dilettante",
  "DragSelectable": true,
  "GMNotes_path": "AllPlayerCards.15bb07/JennyBarnes.9058d3.gmnotes",
  "GUID": "9058d3",
  "Grid": true,
  "GridProjection": false,
  "Hands": true,
  "HideWhenFaceDown": false,
  "IgnoreFoW": false,
  "LayoutGroupSortIndex": 0,
  "Locked": false,
  "LuaScript": "",
  "LuaScriptState": "",
  "MeasureMovement": false,
  "Name": "Card",
  "Nickname": "Jenny Barnes",
  "SidewaysCard": true,
  "Snap": true,
  "States": {
    "2": {
      "AltLookAngle": {
        "x": 0,
        "y": 0,
        "z": 0
      },
      "Autoraise": true,
      "CardID": 273631,
      "ColorDiffuse": {
        "b": 0.713235259,
        "g": 0.713235259,
        "r": 0.713235259
      },
      "CustomDeck": {
        "2736": {
          "BackIsHidden": true,
          "BackURL": "http://cloud-3.steamusercontent.com/ugc/1011562618093845464/80687C9319FA2015F3D9F7CBEB4C55FBF045B27D/",
          "FaceURL": "http://cloud-3.steamusercontent.com/ugc/1011562618093845971/A678BD374EC4DE672206B5EF7EB57DC885BC839C/",
          "NumHeight": 7,
          "NumWidth": 10,
          "Type": 0,
          "UniqueBack": true
        }
      },
      "Description": "The Dilettante",
      "DragSelectable": true,
      "GMNotes": "{\r\n  \"id\": \"02003\",\r\n  \"alternate_ids\": [\r\n    \"98001\"\r\n  ],\r\n  \"type\": \"Investigator\",\r\n  \"class\": \"Rogue\",\r\n  \"traits\": \"Drifter.\",\r\n  \"willpowerIcons\": 3,\r\n  \"intellectIcons\": 3,\r\n  \"combatIcons\": 3,\r\n  \"agilityIcons\": 3,\r\n  \"cycle\": \"The Dunwich Legacy\",\r\n  \"deck_requirements\": {\r\n    \"size\": 30,\r\n    \"randomBasicWeaknessCount\": 1,\r\n    \"signatures\": {\r\n      \"02010\": {\r\n        \"98002\": 1,\r\n        \"02010\": 1\r\n      },\r\n      \"02011\": {\r\n        \"98003\": 1,\r\n        \"02011\": 1\r\n      }\r\n    }\r\n  },\r\n  \"deck_options\": [\r\n    {\r\n      \"faction\": [\r\n        \"rogue\",\r\n        \"neutral\"\r\n      ],\r\n      \"level\": {\r\n        \"min\": 0,\r\n        \"max\": 5\r\n      }\r\n    },\r\n    {\r\n      \"level\": {\r\n        \"min\": 0,\r\n        \"max\": 0\r\n      },\r\n      \"limit\": 5,\r\n      \"error\": \"You cannot have more than 5 cards that are not Rogue or Neutral\"\r\n    }\r\n  ]\r\n}\r\n",
      "GUID": "b954f6",
      "Grid": true,
      "GridProjection": false,
      "Hands": true,
      "HideWhenFaceDown": false,
      "IgnoreFoW": false,
      "LayoutGroupSortIndex": 0,
      "Locked": false,
      "LuaScript": "",
      "LuaScriptState": "",
      "MeasureMovement": false,
      "Name": "Card",
      "Nickname": "Jenny Barnes (promo version)",
      "SidewaysCard": true,
      "Snap": true,
      "Sticky": true,
      "Tags": [
        "Investigator",
        "PlayerCard"
      ],
      "Tooltip": true,
      "Transform": {
        "posX": 9.175334,
        "posY": 1.49510384,
        "posZ": 21.4800034,
        "rotX": 5.375201e-8,
        "rotY": 180,
        "rotZ": -3.88488473e-7,
        "scaleX": 1.15,
        "scaleY": 1,
        "scaleZ": 1.15
      },
      "Value": 0,
      "XmlUI": ""
    }
  },
  "Sticky": true,
  "Tags": [
    "Investigator",
    "PlayerCard"
  ],
  "Tooltip": true,
  "Transform": {
    "posX": 26.925,
    "posY": 3.688,
    "posZ": -2.775,
    "rotX": 0,
    "rotY": 270,
    "rotZ": 0,
    "scaleX": 1.15,
    "scaleY": 1,
    "scaleZ": 1.15
  },
  "Value": 0,
  "XmlUI": ""
}
