{
  "AltLookAngle": {
    "x": 0,
    "y": 0,
    "z": 0
  },
  "Autoraise": true,
  "CardID": 12100,
  "ColorDiffuse": {
    "b": 0.71324,
    "g": 0.71324,
    "r": 0.71324
  },
  "CustomDeck": {
    "121": {
      "BackIsHidden": true,
      "BackURL": "http://cloud-3.steamusercontent.com/ugc/2279448008875867646/87E93B4F71674659B01C9ED280E573D7BD929882/",
      "FaceURL": "http://cloud-3.steamusercontent.com/ugc/2279448008875867768/A54D29440DD5A9DA4E059B861C7AC22F5ACD9BE4/",
      "NumHeight": 1,
      "NumWidth": 1,
      "Type": 0,
      "UniqueBack": false
    }
  },
  "Description": "The Scientist",
  "DragSelectable": true,
  "GMNotes_path": "AllPlayerCards.15bb07/KateWinthrop.ce2322.gmnotes",
  "GUID": "ce2322",
  "Grid": true,
  "GridProjection": false,
  "Hands": true,
  "HideWhenFaceDown": true,
  "IgnoreFoW": false,
  "LayoutGroupSortIndex": 0,
  "Locked": false,
  "LuaScript": "",
  "LuaScriptState": "",
  "MeasureMovement": false,
  "Name": "CardCustom",
  "Nickname": "Kate Winthrop",
  "SidewaysCard": true,
  "Snap": true,
  "Sticky": true,
  "Tags": [
    "Investigator",
    "PlayerCard"
  ],
  "Tooltip": true,
  "Transform": {
    "posX": 9.227,
    "posY": 3.548,
    "posZ": 2.42,
    "rotX": 0,
    "rotY": 180,
    "rotZ": 0,
    "scaleX": 1.15,
    "scaleY": 1,
    "scaleZ": 1.15
  },
  "Value": 0,
  "XmlUI": ""
}
