{
  "AltLookAngle": {
    "x": 0,
    "y": 0,
    "z": 0
  },
  "Autoraise": true,
  "CardID": 368852,
  "ColorDiffuse": {
    "b": 0.713235259,
    "g": 0.713235259,
    "r": 0.713235259
  },
  "CustomDeck": {
    "3688": {
      "BackIsHidden": true,
      "BackURL": "https://i.imgur.com/EcbhVuh.jpg/",
      "FaceURL": "http://cloud-3.steamusercontent.com/ugc/960860672864134253/9A6E0399D3624C5FFBD6CAFE5D4B988436CC65AC/",
      "NumHeight": 7,
      "NumWidth": 10,
      "Type": 0,
      "UniqueBack": false
    }
  },
  "Description": "Big Man on Campus",
  "DragSelectable": true,
  "GMNotes": "{\n  \"id\": \"02035\",\n  \"type\": \"Asset\",\n  \"class\": \"Survivor\",\n  \"cost\": 3,\n  \"level\": 2,\n  \"traits\": \"Ally. Miskatonic.\",\n  \"permanent\": false,\n  \"weakness\": false,\n  \"willpowerIcons\": 1,\n  \"cycle\": \"The Dunwich Legacy\"\n}",
  "GUID": "e1e098",
  "Grid": true,
  "GridProjection": false,
  "Hands": true,
  "HideWhenFaceDown": true,
  "IgnoreFoW": false,
  "LayoutGroupSortIndex": 0,
  "Locked": false,
  "LuaScript": "",
  "LuaScriptState": "",
  "MeasureMovement": false,
  "Name": "Card",
  "Nickname": "Peter Sylvestre (2)",
  "SidewaysCard": false,
  "Snap": true,
  "Sticky": true,
  "Tags": [
    "PlayerCard",
    "Asset"
  ],
  "Tooltip": true,
  "Transform": {
    "posX": 8.987807,
    "posY": 3.678501,
    "posZ": -16.6919117,
    "rotX": 359.939636,
    "rotY": 270.014343,
    "rotZ": 0.0121479128,
    "scaleX": 1,
    "scaleY": 1,
    "scaleZ": 1
  },
  "Value": 0,
  "XmlUI": ""
}