{
  "AltLookAngle": {
    "x": 0,
    "y": 0,
    "z": 0
  },
  "Autoraise": true,
  "CardID": 267601,
  "ColorDiffuse": {
    "b": 0.71324,
    "g": 0.71324,
    "r": 0.71324
  },
  "CustomDeck": {
    "2676": {
      "BackIsHidden": true,
      "BackURL": "https://steamusercontent-a.akamaihd.net/ugc/62595225072374541/B14D307A7F0D747FC791710A1414316530AD372C/",
      "FaceURL": "https://steamusercontent-a.akamaihd.net/ugc/62595225072374002/EF37D6C0713D795835D0E78CC78DF648C77C25A6/",
      "NumHeight": 2,
      "NumWidth": 4,
      "Type": 0,
      "UniqueBack": true
    }
  },
  "Description": "Blind Devotion",
  "DragSelectable": true,
  "GMNotes_path": "AllPlayerCards.15bb07/WalkinFaith.da957e.gmnotes",
  "GUID": "da957e",
  "Grid": true,
  "GridProjection": false,
  "Hands": true,
  "HideWhenFaceDown": false,
  "IgnoreFoW": false,
  "LayoutGroupSortIndex": 0,
  "Locked": false,
  "LuaScript": "",
  "LuaScriptState": "",
  "MeasureMovement": false,
  "Name": "Card",
  "Nickname": "Walk in Faith",
  "SidewaysCard": false,
  "Snap": true,
  "Sticky": true,
  "Tags": [
    "Asset",
    "PlayerCard"
  ],
  "Tooltip": true,
  "Transform": {
    "posX": 73.038,
    "posY": 47.36,
    "posZ": -9.084,
    "rotX": 0,
    "rotY": 270,
    "rotZ": 0,
    "scaleX": 1,
    "scaleY": 1,
    "scaleZ": 1
  },
  "Value": 0,
  "XmlUI": ""
}
