{
  "AltLookAngle": {
    "x": 0,
    "y": 0,
    "z": 0
  },
  "Autoraise": true,
  "ColorDiffuse": {
    "b": 0.713235259,
    "g": 0.713235259,
    "r": 0.713235259
  },
  "ContainedObjects_path": "LionsEncounterSet.c7b914",
  "CustomDeck": {
    "2685": {
      "BackIsHidden": true,
      "BackURL": "http://cloud-3.steamusercontent.com/ugc/1461933361191993988/FE126C3E21593398897E3C691A0AEA8D9B73A614/",
      "FaceURL": "http://cloud-3.steamusercontent.com/ugc/1847049778276374906/B534C97542A0BE04B2398A69A6C6DB85A05DA1F6/",
      "NumHeight": 2,
      "NumWidth": 2,
      "Type": 0,
      "UniqueBack": false
    }
  },
  "DeckIDs": [
    268500,
    268501
  ],
  "Description": "",
  "DragSelectable": true,
  "GMNotes": "",
  "GUID": "c7b914",
  "Grid": true,
  "GridProjection": false,
  "Hands": false,
  "HideWhenFaceDown": true,
  "IgnoreFoW": false,
  "LayoutGroupSortIndex": 0,
  "Locked": false,
  "LuaScript": "",
  "LuaScriptState": "",
  "MeasureMovement": false,
  "Name": "Deck",
  "Nickname": "Lions Encounter Set",
  "SidewaysCard": false,
  "Snap": true,
  "Sticky": true,
  "Tooltip": true,
  "Transform": {
    "posX": 17.6111126,
    "posY": 2.00257015,
    "posZ": -103.60244,
    "rotX": 0.02081094,
    "rotY": 269.9936,
    "rotZ": 0.0167689677,
    "scaleX": 1,
    "scaleY": 1,
    "scaleZ": 1
  },
  "Value": 0,
  "XmlUI": ""
}