{
  "AltLookAngle": {
    "x": 0,
    "y": 0,
    "z": 0
  },
  "Autoraise": true,
  "ColorDiffuse": {
    "b": 0.71324,
    "g": 0.71324,
    "r": 0.71324
  },
  "ContainedObjects_order": [
    "CardCustom.014f43",
    "CardCustom.529780",
    "CardCustom.bb7fd1",
    "CardCustom.9afb3c",
    "CardCustom.4184a4",
    "CardCustom.39573d",
    "CardCustom.abaae3",
    "CardCustom.8c5529"
  ],
  "ContainedObjects_path": "Memories.75101d",
  "CustomDeck": {
    "3186": {
      "BackIsHidden": true,
      "BackURL": "https://i.imgur.com/sRsWiSG.jpg/",
      "FaceURL": "https://i.imgur.com/qfJPZXC.png",
      "NumHeight": 1,
      "NumWidth": 1,
      "Type": 0,
      "UniqueBack": false
    },
    "3187": {
      "BackIsHidden": true,
      "BackURL": "https://i.imgur.com/sRsWiSG.jpg/",
      "FaceURL": "https://i.imgur.com/V9mb5vC.png",
      "NumHeight": 1,
      "NumWidth": 1,
      "Type": 0,
      "UniqueBack": false
    },
    "3188": {
      "BackIsHidden": true,
      "BackURL": "https://i.imgur.com/sRsWiSG.jpg/",
      "FaceURL": "https://i.imgur.com/YKQaQ5U.png",
      "NumHeight": 1,
      "NumWidth": 1,
      "Type": 0,
      "UniqueBack": false
    },
    "3189": {
      "BackIsHidden": true,
      "BackURL": "https://i.imgur.com/sRsWiSG.jpg/",
      "FaceURL": "https://i.imgur.com/9dYUyFk.png",
      "NumHeight": 1,
      "NumWidth": 1,
      "Type": 0,
      "UniqueBack": false
    },
    "3191": {
      "BackIsHidden": true,
      "BackURL": "https://i.imgur.com/sRsWiSG.jpg/",
      "FaceURL": "https://i.imgur.com/GpIOqRC.png",
      "NumHeight": 1,
      "NumWidth": 1,
      "Type": 0,
      "UniqueBack": false
    },
    "3192": {
      "BackIsHidden": true,
      "BackURL": "https://i.imgur.com/sRsWiSG.jpg/",
      "FaceURL": "https://i.imgur.com/esX73Eq.png",
      "NumHeight": 1,
      "NumWidth": 1,
      "Type": 0,
      "UniqueBack": false
    },
    "3193": {
      "BackIsHidden": true,
      "BackURL": "https://i.imgur.com/sRsWiSG.jpg/",
      "FaceURL": "https://i.imgur.com/8HR5dwM.png",
      "NumHeight": 1,
      "NumWidth": 1,
      "Type": 0,
      "UniqueBack": false
    },
    "3194": {
      "BackIsHidden": true,
      "BackURL": "https://i.imgur.com/sRsWiSG.jpg/",
      "FaceURL": "https://i.imgur.com/GzgwPaa.png",
      "NumHeight": 1,
      "NumWidth": 1,
      "Type": 0,
      "UniqueBack": false
    }
  },
  "DeckIDs": [
    318600,
    318700,
    318800,
    318900,
    319100,
    319200,
    319300,
    319400
  ],
  "Description": "",
  "DragSelectable": true,
  "GMNotes": "",
  "GUID": "75101d",
  "Grid": true,
  "GridProjection": false,
  "Hands": false,
  "HideWhenFaceDown": true,
  "IgnoreFoW": false,
  "LayoutGroupSortIndex": 0,
  "Locked": false,
  "LuaScript": "",
  "LuaScriptState": "",
  "MeasureMovement": false,
  "Name": "Deck",
  "Nickname": "Memories",
  "SidewaysCard": false,
  "Snap": true,
  "Sticky": true,
  "Tooltip": true,
  "Transform": {
    "posX": 15.738,
    "posY": 1.481,
    "posZ": 4.5,
    "rotX": 0,
    "rotY": 270,
    "rotZ": 180,
    "scaleX": 1,
    "scaleY": 1,
    "scaleZ": 1
  },
  "Value": 0,
  "XmlUI": ""
}
